stitchtoon/__init__.py
stitchtoon/__main__.py
stitchtoon/detectors/__init__.py
stitchtoon/detectors/direct_slicing.py
stitchtoon/detectors/metadata_slicing.py
stitchtoon/detectors/pixel_comparison.py
stitchtoon/detectors/selector.py
stitchtoon/services/__init__.py
stitchtoon/services/global_logger.py
stitchtoon/services/image_directory.py
stitchtoon/services/image_handler.py
stitchtoon/services/image_manipulator.py
stitchtoon/services/postprocess_runner.py
stitchtoon/services/process.py
stitchtoon/services/progressbar.py
stitchtoon/services/scanner.py
stitchtoon/utils/__init__.py
stitchtoon/utils/constants.py
stitchtoon/utils/errors.py
stitchtoon/utils/funcs.py
stitchtoon-1.2.1.dist-info/entry_points.txt
stitchtoon-1.2.1.dist-info/LICENSE
stitchtoon-1.2.1.dist-info/WHEEL
stitchtoon-1.2.1.dist-info/METADATA
stitchtoon-1.2.1.dist-info/RECORD
