Metadata-Version: 2.1
Name: stitchtoon
Version: 1.2.1
Summary: A powerful program for stitching and cutting webtoons/manhwa/manhua raws.
Keywords: manga,webtoon,stitch,slice,combin
Author-email: Beshr Alghalil <beshrghalil@protonmail.com>
Requires-Python: >=3.8
Classifier: Programming Language :: Python :: 3
Classifier: License :: OSI Approved :: MIT License
Classifier: Operating System :: OS Independent
Requires-Dist: psd_tools
Requires-Dist: natsort
Requires-Dist: pillow
Requires-Dist: progress
Requires-Dist: black ; extra == "dev"
Requires-Dist: flake8 ; extra == "dev"
Requires-Dist: isort ; extra == "dev"
Requires-Dist: tox ; extra == "dev"
Requires-Dist: mypy ; extra == "dev"
Requires-Dist: pytest ; extra == "test"
Project-URL: Bug Tracker, https://github.com/BishrGhalil/issues
Project-URL: Homepage, https://github.com/BishrGhalil/stitchtoon
Provides-Extra: dev
Provides-Extra: test
